graphforge/__init__.py
graphforge/api.py
graphforge/ast/__init__.py
graphforge/ast/clause.py
graphforge/ast/expression.py
graphforge/ast/pattern.py
graphforge/ast/query.py
graphforge/executor/__init__.py
graphforge/executor/evaluator.py
graphforge/executor/executor.py
graphforge/parser/__init__.py
graphforge/parser/cypher.lark
graphforge/parser/parser.py
graphforge/planner/__init__.py
graphforge/planner/operators.py
graphforge/planner/planner.py
graphforge/storage/__init__.py
graphforge/storage/memory.py
graphforge/storage/serialization.py
graphforge/storage/sqlite_backend.py
graphforge/types/__init__.py
graphforge/types/graph.py
graphforge/types/values.py
graphforge-0.1.2.dist-info/METADATA
graphforge-0.1.2.dist-info/WHEEL
graphforge-0.1.2.dist-info/licenses/LICENSE
graphforge-0.1.2.dist-info/RECORD
