Metadata-Version: 2.4
Name: graphforge
Version: 0.1.2
Summary: Composable graph tooling for analysis, construction, and refinement
Project-URL: Homepage, https://github.com/DecisionNerd/graphforge
Project-URL: Repository, https://github.com/DecisionNerd/graphforge
Project-URL: Issues, https://github.com/DecisionNerd/graphforge/issues
Author: David Spencer
License: MIT
License-File: LICENSE
Keywords: analysis,graph,opencypher,pydantic
Requires-Python: >=3.10
Requires-Dist: lark>=1.1
Requires-Dist: msgpack>=1.0
Requires-Dist: pydantic>=2.6
Requires-Dist: pyyaml>=6.0.3
Provides-Extra: dev
Requires-Dist: hypothesis>=6.0; extra == 'dev'
Requires-Dist: pytest-bdd>=7.0; extra == 'dev'
Requires-Dist: pytest-cov>=4.0; extra == 'dev'
Requires-Dist: pytest-mock>=3.0; extra == 'dev'
Requires-Dist: pytest-timeout>=2.0; extra == 'dev'
Requires-Dist: pytest-xdist>=3.0; extra == 'dev'
Requires-Dist: pytest>=7.0; extra == 'dev'
Requires-Dist: ruff>=0.1.0; extra == 'dev'
Provides-Extra: docs
Requires-Dist: mkdocs-autorefs>=1.0.0; extra == 'docs'
Requires-Dist: mkdocs-material>=9.5.0; extra == 'docs'
Requires-Dist: mkdocs>=1.6.0; extra == 'docs'
Requires-Dist: mkdocstrings[python]>=0.24.0; extra == 'docs'
